Workbook

Sheet 使い方
A1: Bunshin Blog サイト設計 構成表（手動作成 第1版）
A3: 対象ジャンル | B3: 実店舗（飲食店）向け業務ツール比較
A4: サイト数 | B4: 1サイト／記事30本（収益7本＋集客23本）
A5: 作成日 | B5: 2026-08-06
A7: この表の位置づけ | B7: M1（構成表ジェネレーター）を実装する前に、手作業でSTEP1〜4を1回通すためのもの。
B8: ここで詰まった箇所が、そのままM1の仕様とテストケースになる。
A10: 記入が必要なセル | B10: 黄色塗り＝必ず埋める／青文字＝入力値（差し替え可）
A12: 作業手順 | B12: 1. 「案件スロット」タブの3案件を、実際のASP案件で確定させる
B13: 2. 案件が変わる場合は「構成表」タブのタイトル・キーワードを合わせて修正する
B14: 3. 収益記事7本を先に公開（1〜2週目）
B15: 4. 集客記事を週4本ずつ公開（3週目以降）
B16: 5. 公開日・インデックス日・順位を記録し、120日ゲートで判定する
A18: 設計ルール（変更する場合はM1の仕様も直す）
A19: 収益記事数 | B19: 採用案件数 × 2 ＋ 1（比較記事）／上限10本
A20: 集客記事から収益記事へのリンク | B20: 各収益記事に最低3本を集める
A21: 1つの集客記事がリンクする収益記事 | B21: 最大2本
A22: 収益記事どうしのリンク | B22: 張らない（回遊させず成果に流す）
A23: 公開ペース | B23: 週4本まで（大量生成と判定されないため）
A24: キーワード重複 | B24: 禁止（同一キーワードで2記事作らない）

Sheet 案件スロット
A1: スロット | B1: 想定カテゴリ | C1: 案件名（要記入） | D1: ASP（要記入） | E1: 報酬額（要記入） | F1: 成果地点 | G1: 成果地点スコア(30) | H1: 報酬額(20) | I1: LPの質(20) | J1: 検索需要(15) | K1: 利用経験(10) | L1: 否認条件(5) | M1: 合計
A2: A | B2: 予約管理システム | F2: 無料登録・無料プラン申込 | M2: =SUM(G2:L2) -> 0
A3: B | B3: モバイルオーダー／セルフオーダー | F3: 資料請求・無料デモ申込 | M3: =SUM(G3:L3) -> 0
A4: C | B4: MEO・店舗集客ツール | F4: 資料請求・無料診断申込 | M4: =SUM(G4:L4) -> 0
A6: 記入例（この行は削除してよい）
A7: 例 | B7: 予約管理システム | C7: ○○予約(無料プラン) | D7: A8.net | E7: 1,500円 | F7: 無料プラン登録 | G7: 30 | H7: 8 | I7: 16 | J7: 12 | K7: 10 | L7: 4 | M7: =SUM(G7:L7) -> 80
A10: 採用基準：合計60点未満しか無い場合はジャンルごとSTEP1に差し戻す
A11: 足切り：掲載終了／購入必須かつ単価3,000円未満／否認条件3つ以上／LPスマホ非対応／ブログ掲載禁止
A12: 追加足切り：無料登録型でも単価800円未満は除外（成果は出るが収益にならないため）
A13: LPの質の判定：フォーム項目5個以下=20点／6〜10個=10点／11個以上=0点
A14: 成果地点スコア：無料登録30／資料請求20／無料体験15／購入10

Sheet 構成表
A1: No | B1: 種別 | C1: 想定タイトル | D1: 狙うキーワード | E1: 検索意図（読者の状態） | F1: リンク先No | G1: 使用案件 | H1: 公開予定週 | I1: 公開日 | J1: インデックス日 | K1: 順位 | L1: 備考
A2: 1 | B2: 収益 | C2: 【案件A】の口コミ・評判｜実際に使った店舗の声 | D2: 案件A名 口コミ | E2: 導入をほぼ決めていて最後の確認をしている | F2: - | G2: A | H2: 1
A3: 2 | B3: 収益 | C3: 【案件A】の料金プランと解約方法をまとめて解説 | D3: 案件A名 料金 | E3: 費用と抜けやすさを確認している | F3: - | G3: A | H3: 1
A4: 3 | B4: 収益 | C4: 【案件B】の口コミ・評判｜導入店舗のリアルな評価 | D4: 案件B名 評判 | E4: 導入をほぼ決めていて最後の確認をしている | F4: - | G4: B | H4: 1
A5: 4 | B5: 収益 | C5: 【案件B】の料金と導入手順｜初期費用はいくらか | D5: 案件B名 導入 費用 | E5: 初期費用と手間を確認している | F5: - | G5: B | H5: 2
A6: 5 | B6: 収益 | C6: 【案件C】の口コミ・評判｜効果はあったのか | D6: 案件C名 口コミ | E6: 効果の実在を疑いつつ確認している | F6: - | G6: C | H6: 2
A7: 6 | B7: 収益 | C7: 【案件C】の料金と解約条件｜契約前に確認すべき点 | D7: 案件C名 解約 | E7: 契約リスクを確認している | F7: - | G7: C | H7: 2
A8: 7 | B8: 収益 | C8: 飲食店向け業務ツール比較｜予約・注文・集客の3分野 | D8: 飲食店 業務ツール 比較 | E8: 何を導入すべきか決まっていない | F8: - | G8: A/B/C | H8: 2
A9: 8 | B9: 集客 | C9: 飲食店の予約電話を減らす方法｜営業中の中断をなくす | D9: 飲食店 予約 電話 減らす | E9: 電話対応の負担に困っている | F9: 1,7 | G9: - | H9: 3
A10: 9 | B10: 集客 | C10: 無断キャンセル対策｜個人店でもできる5つの方法 | D10: 無断キャンセル 対策 飲食店 | E10: 実損が出て対策を探している | F10: 1 | G10: - | H10: 3
A11: 10 | B11: 集客 | C11: 予約台帳を手書きで管理するデメリットと限界 | D11: 予約台帳 手書き | E11: 現状のやり方に不安を感じている | F11: 1,2 | G11: - | H11: 3
A12: 11 | B12: 集客 | C12: 飲食店の予約システムの選び方｜失敗しない5つの基準 | D12: 飲食店 予約システム 選び方 | E12: 導入を検討し始めた | F12: 1,2 | G12: - | H12: 3
A13: 12 | B13: 集客 | C13: 飲食店の人手不足はなぜ起きるのか｜構造と対処法 | D13: 飲食店 人手不足 対策 | E13: 採用できず困っている | F13: 3,7 | G13: - | H13: 4
... A31: 30 | B31: 集客 | C31: 飲食店の原価率を下げる方法｜削ってはいけない部分 | D31: 飲食店 原価率 下げる | E31: 利益が残らない | F31: 7 | G31: - | H31: 8

Sheet 制約チェック
A1: 制約チェック（M1に実装する検証ロジック）
A3: 項目 | B3: 基準 | C3: 実測 | D3: 判定
A4: 記事総数 | B4: 30 | C4: =COUNTA(構成表!A2:A31) -> 30 | D4: =IF(C4>=B4,"OK","要修正") -> OK
A5: 収益記事数 | B5: 7 | C5: =COUNTIF(構成表!B2:B31,"収益") -> 7 | D5: =IF(C5>=B5,"OK","要修正") -> OK
A6: 集客記事数 | B6: 23 | C6: =COUNTIF(構成表!B2:B31,"集客") -> 23 | D6: =IF(C6>=B6,"OK","要修正") -> OK
A7: 収益記事No.1 への流入本数 | B7: 3 | C7: =SUMPRODUCT(--ISNUMBER(SEARCH(",1,",","&構成表!F9:F31&","))) -> 6 | D7: =IF(C7>=B7,"OK","要修正") -> OK
A8: 収益記事No.2 への流入本数 | B8: 3 | C8: =SUMPRODUCT(--ISNUMBER(SEARCH(",2,",","&構成表!F9:F31&","))) -> 3 | D8: =IF(C8>=B8,"OK","要修正") -> OK
A9: 収益記事No.3 への流入本数 | B9: 3 | C9: =SUMPRODUCT(--ISNUMBER(SEARCH(",3,",","&構成表!F9:F31&","))) -> 5 | D9: =IF(C9>=B9,"OK","要修正") -> OK
A10: 収益記事No.4 への流入本数 | B10: 3 | C10: =SUMPRODUCT(--ISNUMBER(SEARCH(",4,",","&構成表!F9:F31&","))) -> 6 | D10: =IF(C10>=B10,"OK","要修正") -> OK
A11: 収益記事No.5 への流入本数 | B11: 3 | C11: =SUMPRODUCT(--ISNUMBER(SEARCH(",5,",","&構成表!F9:F31&","))) -> 5 | D11: =IF(C11>=B11,"OK","要修正") -> OK
A12: 収益記事No.6 への流入本数 | B12: 3 | C12: =SUMPRODUCT(--ISNUMBER(SEARCH(",6,",","&構成表!F9:F31&","))) -> 4 | D12: =IF(C12>=B12,"OK","要修正") -> OK
A13: 収益記事No.7 への流入本数 | B13: 3 | C13: =SUMPRODUCT(--ISNUMBER(SEARCH(",7,",","&構成表!F9:F31&","))) -> 10 | D13: =IF(C13>=B13,"OK","要修正") -> OK
A16: M1（構成表ジェネレーター）に実装する再生成ループ：
A17: 1. 収益記事を案件から生成
A18: 2. 各収益記事に繋ぐ検索意図を3つ列挙
A19: 3. 検索意図をキーワードに変換
A20: 4. キーワード重複を検出し統合または差し替え
A21: 5. 上記の制約を全て満たすまで 2〜4 を再実行（最大3回）
A22: 6. 公開順序を付与（収益記事を先に全公開 → 集客記事を週4本）
A24: 手動作成で判明した論点（M1の仕様に反映すること）：
A25: ・検索意図からキーワードへの変換で、重複が発生しやすい（例：集客/選び方/比較）
A26: ・1つの集客記事が2本の収益記事に繋がると、記事内容がぶれやすい
A27: ・案件名が確定しないと収益記事のタイトルが作れない → 案件確定を必須の前工程にする
A28: ・リンク先に集客記事の番号を書いてしまう誤りが多発した → M1では収益記事のNoのみ許可するバリデーションが必須
A29: ・料金・解約系の収益記事は流入を集めにくい（初回は1本しか繋がらなかった）→ 費用/補助金系の集客記事を意図的に割り当てる
